[{"stepRecords":[],"scaleX":1,"scaleY":1,"orientation":0,"topOffset":0,"width":21,"axesPosX":1,"leftOffset":0,"axesPosY":72,"dpi":96,"items":[{"rotation":-0.007873852737247944,"contentFormat":"{\"charset\":\"GBK\",\"autoGp\":true,\"gpNum\":1,\"firstLineAlign\":\"NONE\"}","name":"元素3","x":15,"pageInfo":{"disableTrans":false,"leftGap":0,"alignOffsetX":0,"topGap":0,"bottomGap":0,"alignOffsetY":0,"baseLine":0,"lineGap":7,"alignOffsetXMax":0,"pageHeight":198.50465,"numShowPage":1,"pageWidth":142.97992,"space":1,"contentDir":0,"rightGapMax":0,"lineNum2":0,"selfAdaption":false,"fontChance":[1],"fontPath":["blood8真迹2_kvenjoy_blood8.gfont"],"contentAlign":"Left","pageRotateType":0,"rotation":0,"alignOffsetYMax":0,"leftGapMax":0,"lineGapOffset":-0.5,"isDefault":false,"topGapMax":0,"showPageGap":0,"selfAdaptionNoNewLine":false,"lineNum":0,"fontSize":100,"rightGap":0},"width":540.3965454101562,"y":73,"text":"(1)画出由74LS194、74LS161、74LS290构成的计数器的状态转换图\n四位右移环形计数器\n\n\n四位右移扭环形计数器\n\n\n\n六进制计数器(74LS161). \n\n\n\n六进制计数器(74LS290)\n(2)说明用异步复位法与同步置数法实现任意进制计数器.有何不同之处?各自有好什么优缺点？＞ 优点：精确控制＋低功耗，缺点：设计复杂度＋时序问题.\n答：异步复位法提供了更细粒度的控制，但可能增加.设计复杂度与引入时序问题，101而同步置数法相对简单，但无法单独控制每个位，且可能造成不必要的同时置数\n优点：简单性与同步性.缺点：限制性＋可能增加功耗\n(3)利用74LS290是否可以完成74LS160的功能?反之如何\n答：可以.如下图接线可实现＋进制计数器.\n（但无法实现进位）、\n反之74LS160也可实现74LS290的功能\n如实现五进制异步加法器","locked":false,"type":"text","height":750.2538452148438}],"height":29.700000762939453}]